ppdeep.py
ppdeep-20251115.dist-info/METADATA
ppdeep-20251115.dist-info/WHEEL
ppdeep-20251115.dist-info/top_level.txt
ppdeep-20251115.dist-info/RECORD
