Metadata-Version: 2.1
Name: ppdeep
Version: 20251115
Summary: Pure-Python library for computing fuzzy hashes (ssdeep)
Home-page: https://github.com/elceef/ppdeep
Author: Marcin Ulikowski
Author-email: marcin@ulikowski.pl
License: ASL 2.0
Platform: UNKNOWN
Classifier: Programming Language :: Python :: 3
Classifier: License :: OSI Approved :: Apache Software License
Classifier: Operating System :: OS Independent
